twtender/__init__.py
twtender/api.py
twtender/main.py
twtender-0.1.0.dist-info/LICENSE
twtender-0.1.0.dist-info/METADATA
twtender-0.1.0.dist-info/WHEEL
twtender-0.1.0.dist-info/entry_points.txt
twtender-0.1.0.dist-info/top_level.txt
twtender-0.1.0.dist-info/RECORD
