Metadata-Version: 2.1
Name: twtender
Version: 0.1.0
Summary: API to get tenders from Taiwan
Home-page: https://github.com/hunglin59638/twtender
Author: Hung-Lin, Chen
Author-email: hunglin59638@gmail.com
Maintainer: Hung-Lin, Chen
Maintainer-email: hunglin59638@gmail.com
License: UNKNOWN
Platform: UNKNOWN
Requires-Python: >=3.10,<4.0
License-File: LICENSE
Requires-Dist: bs4 (<0.0.3,>=0.0.2)
Requires-Dist: click (<9.0.0,>=8.1.7)
Requires-Dist: fastapi-class (<4.0.0,>=3.6.0)
Requires-Dist: fastapi (<0.116.0,>=0.115.4)
Requires-Dist: pandas (<3.0.0,>=2.2.3)
Requires-Dist: requests (<3.0.0,>=2.32.3)
Requires-Dist: toml (<0.11.0,>=0.10.2)
Requires-Dist: uvicorn (<0.33.0,>=0.32.0)
